CHANGELOG.txt
LICENCE.txt
MANIFEST.in
README.txt
setup.py
moduletesting/__init__.py
moduletesting.egg-info/PKG-INFO
moduletesting.egg-info/SOURCES.txt
moduletesting.egg-info/dependency_links.txt
moduletesting.egg-info/top_level.txt