Metadata-Version: 1.0
Name: moduletesting
Version: 0.0.2
Summary: A simple calculator to test the creation of a python module
Home-page: UNKNOWN
Author: Ulysses-Pacome Koudou
Author-email: up.koudou@gmail.com
License: MIT
Platform: UNKNOWN
